README.md
setup.py
jupphelp/__init__.py
jupphelp/helper.py
jupphelp.egg-info/PKG-INFO
jupphelp.egg-info/SOURCES.txt
jupphelp.egg-info/dependency_links.txt
jupphelp.egg-info/entry_points.txt
jupphelp.egg-info/requires.txt
jupphelp.egg-info/top_level.txt