Metadata-Version: 2.1
Name: jupphelp
Version: 0.1.0
Requires-Dist: requests
